mail_parser-4.1.3.dist-info/licenses/LICENSE.txt
mail_parser-4.1.3.dist-info/licenses/NOTICE.txt
mailparser/__init__.py
mailparser/__main__.py
mailparser/const.py
mailparser/core.py
mailparser/exceptions.py
mailparser/utils.py
mailparser/version.py
mail_parser-4.1.3.dist-info/METADATA
mail_parser-4.1.3.dist-info/WHEEL
mail_parser-4.1.3.dist-info/entry_points.txt
mail_parser-4.1.3.dist-info/top_level.txt
mail_parser-4.1.3.dist-info/RECORD
