Metadata-Version: 2.4
Name: mail-parser
Version: 4.1.3
Summary: Improved wrapper for email standard library
Home-page: https://github.com/SpamScope/mail-parser
Author: Fedele Mantuano
Author-email: mantuano.fedele@gmail.com
Maintainer: Fedele Mantuano
Maintainer-email: mantuano.fedele@gmail.com
License: Apache License, Version 2.0
Keywords: email,mail,parser,spam,phishing,malware,forensic,analysis
Platform: OS Independent
Classifier: License :: OSI Approved :: Apache Software License
Classifier: Operating System :: OS Independent
Classifier: Natural Language :: English
Classifier: Programming Language :: Python
Classifier: Programming Language :: Python :: 3
Classifier: Programming Language :: Python :: 3.8
Classifier: Programming Language :: Python :: 3.9
Classifier: Programming Language :: Python :: 3.10
Requires-Python: >=3.8
License-File: LICENSE.txt
License-File: NOTICE.txt
Requires-Dist: six
Provides-Extra: dev
Requires-Dist: build; extra == "dev"
Requires-Dist: pre-commit; extra == "dev"
Requires-Dist: wheel; extra == "dev"
Requires-Dist: twine; extra == "dev"
Provides-Extra: test
Requires-Dist: coverage; extra == "test"
Requires-Dist: pytest; extra == "test"
Requires-Dist: pytest-cov; extra == "test"
Requires-Dist: pytest-mock; extra == "test"
Requires-Dist: pytest-ordering; extra == "test"
Dynamic: license-file
